ptrepl/__init__.py
ptrepl/cli.py
ptrepl/completion.py
ptrepl/config.py
ptrepl/history.py
ptrepl/prompt.py
ptrepl/toolbars.py
ptrepl/bash/__init__.py
ptrepl/bash/history.py
ptrepl/bash/prompt.py
ptrepl/vendor/__init__.py
ptrepl/vendor/bash_completion.py
ptrepl-0.9.8.dist-info/LICENSE
ptrepl-0.9.8.dist-info/METADATA
ptrepl-0.9.8.dist-info/WHEEL
ptrepl-0.9.8.dist-info/entry_points.txt
ptrepl-0.9.8.dist-info/top_level.txt
ptrepl-0.9.8.dist-info/RECORD
