Metadata-Version: 2.1
Name: ptrepl
Version: 0.9.8
Summary: Run command as REPL-environment
Home-page: https://github.com/imomaliev/ptrepl
Author: Sardorbek Imomaliev
License: MIT
Platform: UNKNOWN
Classifier: Development Status :: 6 - Mature
Classifier: Environment :: Console
Classifier: Intended Audience :: Developers
Classifier: Intended Audience :: System Administrators
Classifier: License :: OSI Approved :: MIT License
Classifier: Operating System :: OS Independent
Classifier: Programming Language :: Python :: 3
Classifier: Programming Language :: Python :: 3.6
Classifier: Programming Language :: Python :: 3.7
Classifier: Topic :: Utilities
Requires-Dist: prompt-toolkit (<3.0.0,>=2.0.7)
Requires-Dist: pygments (>=2.3.1)
Requires-Dist: xdg (>=3.0.2)
